[{"reportings":[{"index":3,"score":0.9915243983268738,"category_name":"3 loup"},{"index":5,"score":0.006086062639951706,"category_name":"5 noise"},{"index":1,"score":0.0011543112341314554,"category_name":"1 cerf"},{"index":4,"score":0.0011403677053749561,"category_name":"4 moto-cross"},{"index":0,"score":0.00006861011206638068,"category_name":"0 Bruit de fond"}],"location":"montagne-du-vuache","id":1,"status":"beacon-reconition","created_at":"2023-06-25T21:43:10.590Z","reporting":3},{"reportings":[{"index":3,"score":0.9991047978401184,"category_name":"3 loup"},{"index":5,"score":0.0005294520524330437,"category_name":"5 noise"},{"index":1,"score":0.00027894708910025656,"category_name":"1 cerf"},{"index":4,"score":0.00008207195060094818,"category_name":"4 moto-cross"},{"index":6,"score":0.000003452683131399681,"category_name":"6 renard"}],"location":"montagne-du-vuache","id":2,"status":"beacon-reconition","created_at":"2023-06-25T21:53:21.394Z","reporting":3},{"reportings":[{"index":3,"score":0.92356276512146,"category_name":"3 loup"},{"index":5,"score":0.0729530081152916,"category_name":"5 noise"},{"index":4,"score":0.0024859842378646135,"category_name":"4 moto-cross"},{"index":1,"score":0.000806939322501421,"category_name":"1 cerf"},{"index":0,"score":0.00008234565029852092,"category_name":"0 Bruit de fond"}],"location":"montagne-du-vuache","id":3,"status":"beacon-reconition","created_at":"2023-06-25T21:58:06.477Z","reporting":3},{"reportings":[{"index":1,"score":0.9798172116279602,"category_name":"1 cerf"},{"index":0,"score":0.007457710802555084,"category_name":"0 Bruit de fond"},{"index":5,"score":0.00584549643099308,"category_name":"5 noise"},{"index":3,"score":0.0029949781019240618,"category_name":"3 loup"},{"index":4,"score":0.0019331685034558177,"category_name":"4 moto-cross"}],"location":"montagne-du-vuache","id":4,"status":"beacon-reconition","created_at":"2023-06-25T21:58:39.093Z","reporting":1},{"reportings":[{"index":1,"score":0.9635943174362183,"category_name":"1 cerf"},{"index":5,"score":0.021706530824303627,"category_name":"5 noise"},{"index":3,"score":0.009947353973984718,"category_name":"3 loup"},{"index":4,"score":0.0032057729549705982,"category_name":"4 moto-cross"},{"index":6,"score":0.0010297995759174228,"category_name":"6 renard"}],"location":"montagne-du-vuache","id":5,"status":"beacon-reconition","created_at":"2023-06-25T22:09:56.032Z","reporting":1},{"reportings":[{"index":6,"score":0.9427899122238159,"category_name":"6 renard"},{"index":1,"score":0.026189906522631645,"category_name":"1 cerf"},{"index":0,"score":0.013665576465427876,"category_name":"0 Bruit de fond"},{"index":5,"score":0.009230507537722588,"category_name":"5 noise"},{"index":4,"score":0.0038691277150064707,"category_name":"4 moto-cross"}],"location":"montagne-du-vuache","id":6,"status":"beacon-reconition","created_at":"2023-06-25T22:12:26.702Z","reporting":6},{"reportings":[{"index":3,"score":0.937179684638977,"category_name":"3 loup"},{"index":5,"score":0.054842978715896606,"category_name":"5 noise"},{"index":4,"score":0.0034261925611644983,"category_name":"4 moto-cross"},{"index":1,"score":0.003140833927318454,"category_name":"1 cerf"},{"index":0,"score":0.0008146517211571336,"category_name":"0 Bruit de fond"}],"location":"montagne-du-vuache","id":7,"status":"beacon-reconition","created_at":"2023-06-25T22:12:37.466Z","reporting":3},{"reportings":[{"index":3,"score":0.9178897142410278,"category_name":"3 loup"},{"index":5,"score":0.05709979310631752,"category_name":"5 noise"},{"index":1,"score":0.02294699102640152,"category_name":"1 cerf"},{"index":4,"score":0.0016038650646805763,"category_name":"4 moto-cross"},{"index":6,"score":0.00032002103398554027,"category_name":"6 renard"}],"location":"montagne-du-vuache","id":8,"status":"beacon-reconition","created_at":"2023-06-25T22:15:01.887Z","reporting":3},{"reportings":[{"index":4,"score":0.9667999744415283,"category_name":"4 moto-cross"},{"index":5,"score":0.02915470115840435,"category_name":"5 noise"},{"index":0,"score":0.002917960286140442,"category_name":"0 Bruit de fond"},{"index":1,"score":0.0010632186895236373,"category_name":"1 cerf"},{"index":2,"score":0.00004816924047190696,"category_name":"2 coup_de_feu_chasseur"}],"location":"montagne-du-vuache","id":9,"status":"beacon-reconition","created_at":"2023-06-25T22:17:25.782Z","reporting":4},{"reportings":[{"index":1,"score":0.9463621377944946,"category_name":"1 cerf"},{"index":4,"score":0.025732332840561867,"category_name":"4 moto-cross"},{"index":5,"score":0.012479102239012718,"category_name":"5 noise"},{"index":0,"score":0.010220754891633987,"category_name":"0 Bruit de fond"},{"index":3,"score":0.0026179393753409386,"category_name":"3 loup"}],"location":"montagne-du-vuache","id":10,"status":"beacon-reconition","created_at":"2023-06-25T22:20:41.167Z","reporting":1},{"reportings":[{"index":1,"score":0.990564227104187,"category_name":"1 cerf"},{"index":4,"score":0.005543054081499577,"category_name":"4 moto-cross"},{"index":0,"score":0.001691171433776617,"category_name":"0 Bruit de fond"},{"index":5,"score":0.0010533756576478481,"category_name":"5 noise"},{"index":2,"score":0.0005949697224423289,"category_name":"2 coup_de_feu_chasseur"}],"location":"montagne-du-vuache","id":11,"status":"beacon-reconition","created_at":"2023-06-25T22:24:12.915Z","reporting":1},{"reportings":[{"index":1,"score":0.9945290684700012,"category_name":"1 cerf"},{"index":5,"score":0.0031047349330037832,"category_name":"5 noise"},{"index":4,"score":0.0015982728218659759,"category_name":"4 moto-cross"},{"index":6,"score":0.0002785347169265151,"category_name":"6 renard"},{"index":0,"score":0.00021030298375990242,"category_name":"0 Bruit de fond"}],"location":"montagne-du-vuache","id":12,"status":"beacon-reconition","created_at":"2023-06-25T22:27:25.059Z","reporting":1},{"reportings":[{"index":1,"score":0.9938841462135315,"category_name":"1 cerf"},{"index":4,"score":0.0033923278097063303,"category_name":"4 moto-cross"},{"index":5,"score":0.0014174602692946792,"category_name":"5 noise"},{"index":0,"score":0.0007531000883318484,"category_name":"0 Bruit de fond"},{"index":3,"score":0.00021856307284906507,"category_name":"3 loup"}],"location":"montagne-du-vuache","id":13,"status":"beacon-reconition","created_at":"2023-06-25T22:31:12.636Z","reporting":1},{"reportings":[{"index":1,"score":0.9892020225524902,"category_name":"1 cerf"},{"index":5,"score":0.006294169928878546,"category_name":"5 noise"},{"index":4,"score":0.0015813282225281,"category_name":"4 moto-cross"},{"index":3,"score":0.0011675439309328794,"category_name":"3 loup"},{"index":2,"score":0.0010451901471242309,"category_name":"2 coup_de_feu_chasseur"}],"location":"montagne-du-vuache","id":14,"status":"beacon-reconition","created_at":"2023-06-25T22:32:50.895Z","reporting":1},{"reportings":[{"index":1,"score":0.9849473237991333,"category_name":"1 cerf"},{"index":5,"score":0.007545603904873133,"category_name":"5 noise"},{"index":2,"score":0.0034625271800905466,"category_name":"2 coup_de_feu_chasseur"},{"index":6,"score":0.001669191988185048,"category_name":"6 renard"},{"index":4,"score":0.0011034925701096654,"category_name":"4 moto-cross"}],"location":"montagne-du-vuache","id":15,"status":"beacon-reconition","created_at":"2023-06-25T22:34:01.480Z","reporting":1},{"reportings":[{"index":6,"score":0.902682900428772,"category_name":"6 renard"},{"index":5,"score":0.09017019718885422,"category_name":"5 noise"},{"index":4,"score":0.004737337585538626,"category_name":"4 moto-cross"},{"index":2,"score":0.0008690044633112848,"category_name":"2 coup_de_feu_chasseur"},{"index":3,"score":0.0007061534561216831,"category_name":"3 loup"}],"location":"montagne-du-vuache","id":16,"status":"beacon-reconition","created_at":"2023-06-25T22:39:31.974Z","reporting":6},{"reportings":[{"index":1,"score":0.9945564270019531,"category_name":"1 cerf"},{"index":5,"score":0.0030983646865934134,"category_name":"5 noise"},{"index":4,"score":0.00122632656712085,"category_name":"4 moto-cross"},{"index":0,"score":0.00042551071965135634,"category_name":"0 Bruit de fond"},{"index":3,"score":0.000357808661647141,"category_name":"3 loup"}],"location":"montagne-du-vuache","id":17,"status":"beacon-reconition","created_at":"2023-06-25T22:41:06.059Z","reporting":1},{"reportings":[{"index":1,"score":0.9786175489425659,"category_name":"1 cerf"},{"index":2,"score":0.01316908374428749,"category_name":"2 coup_de_feu_chasseur"},{"index":0,"score":0.004483493510633707,"category_name":"0 Bruit de fond"},{"index":5,"score":0.0020379116758704185,"category_name":"5 noise"},{"index":6,"score":0.0009024526225402951,"category_name":"6 renard"}],"location":"montagne-du-vuache","id":18,"status":"beacon-reconition","created_at":"2023-06-25T22:46:28.778Z","reporting":1},{"reportings":[{"index":1,"score":0.9525203108787537,"category_name":"1 cerf"},{"index":4,"score":0.028885604813694954,"category_name":"4 moto-cross"},{"index":5,"score":0.007023216225206852,"category_name":"5 noise"},{"index":0,"score":0.005728913936764002,"category_name":"0 Bruit de fond"},{"index":2,"score":0.005688013508915901,"category_name":"2 coup_de_feu_chasseur"}],"location":"montagne-du-vuache","id":19,"status":"beacon-reconition","created_at":"2023-06-25T23:00:37.911Z","reporting":1},{"reportings":[{"index":1,"score":0.9181350469589233,"category_name":"1 cerf"},{"index":2,"score":0.03800330311059952,"category_name":"2 coup_de_feu_chasseur"},{"index":6,"score":0.020243391394615173,"category_name":"6 renard"},{"index":5,"score":0.013628961518406868,"category_name":"5 noise"},{"index":4,"score":0.005073915235698223,"category_name":"4 moto-cross"}],"location":"montagne-du-vuache","id":20,"status":"beacon-reconition","created_at":"2023-06-25T23:06:16.071Z","reporting":1},{"reportings":[{"index":1,"score":0.9864387512207031,"category_name":"1 cerf"},{"index":5,"score":0.004727034829556942,"category_name":"5 noise"},{"index":4,"score":0.004040140192955732,"category_name":"4 moto-cross"},{"index":0,"score":0.0037857359275221825,"category_name":"0 Bruit de fond"},{"index":2,"score":0.000818191678263247,"category_name":"2 coup_de_feu_chasseur"}],"location":"montagne-du-vuache","id":21,"status":"beacon-reconition","created_at":"2023-06-25T23:09:01.152Z","reporting":1},{"reportings":[{"index":1,"score":0.9680505394935608,"category_name":"1 cerf"},{"index":2,"score":0.01883685402572155,"category_name":"2 coup_de_feu_chasseur"},{"index":5,"score":0.005990983918309212,"category_name":"5 noise"},{"index":4,"score":0.0037549890112131834,"category_name":"4 moto-cross"},{"index":0,"score":0.0023357700556516647,"category_name":"0 Bruit de fond"}],"location":"montagne-du-vuache","id":22,"status":"beacon-reconition","created_at":"2023-06-25T23:10:53.877Z","reporting":1},{"reportings":[{"index":1,"score":0.9286791086196899,"category_name":"1 cerf"},{"index":2,"score":0.029479321092367172,"category_name":"2 coup_de_feu_chasseur"},{"index":5,"score":0.02255483716726303,"category_name":"5 noise"},{"index":0,"score":0.011684042401611805,"category_name":"0 Bruit de fond"},{"index":4,"score":0.007238355930894613,"category_name":"4 moto-cross"}],"location":"montagne-du-vuache","id":23,"status":"beacon-reconition","created_at":"2023-06-25T23:22:20.840Z","reporting":1},{"reportings":[{"index":3,"score":0.9886630177497864,"category_name":"3 loup"},{"index":5,"score":0.01106876228004694,"category_name":"5 noise"},{"index":4,"score":0.00021052428928669542,"category_name":"4 moto-cross"},{"index":1,"score":0.00004701887155533768,"category_name":"1 cerf"},{"index":6,"score":0.00001007939954433823,"category_name":"6 renard"}],"location":"montagne-du-vuache","id":24,"status":"beacon-reconition","created_at":"2023-06-25T23:22:22.460Z","reporting":3},{"reportings":[{"index":4,"score":0.938846230506897,"category_name":"4 moto-cross"},{"index":0,"score":0.05221909284591675,"category_name":"0 Bruit de fond"},{"index":1,"score":0.006519560236483812,"category_name":"1 cerf"},{"index":5,"score":0.0018012983491644263,"category_name":"5 noise"},{"index":2,"score":0.0006014881655573845,"category_name":"2 coup_de_feu_chasseur"}],"location":"montagne-du-vuache","id":25,"status":"beacon-reconition","created_at":"2023-06-25T23:22:56.675Z","reporting":4},{"reportings":[{"index":6,"score":0.922877311706543,"category_name":"6 renard"},{"index":1,"score":0.041930798441171646,"category_name":"1 cerf"},{"index":4,"score":0.025720590725541115,"category_name":"4 moto-cross"},{"index":2,"score":0.005646586883813143,"category_name":"2 coup_de_feu_chasseur"},{"index":5,"score":0.0024487043265253305,"category_name":"5 noise"}],"location":"montagne-du-vuache","id":26,"status":"beacon-reconition","created_at":"2023-06-25T23:23:08.133Z","reporting":6},{"reportings":[{"index":1,"score":0.9994792342185974,"category_name":"1 cerf"},{"index":5,"score":0.00024025262973736972,"category_name":"5 noise"},{"index":6,"score":0.00014693563571199775,"category_name":"6 renard"},{"index":0,"score":0.00009959148883353919,"category_name":"0 Bruit de fond"},{"index":3,"score":0.000024694645617273636,"category_name":"3 loup"}],"location":"montagne-du-vuache","id":27,"status":"beacon-reconition","created_at":"2023-06-25T23:27:50.769Z","reporting":1},{"reportings":[{"index":3,"score":0.9995806813240051,"category_name":"3 loup"},{"index":1,"score":0.00025969636044465005,"category_name":"1 cerf"},{"index":4,"score":0.00009671926818555221,"category_name":"4 moto-cross"},{"index":5,"score":0.00006165970989968628,"category_name":"5 noise"},{"index":6,"score":0.0000010414809139547287,"category_name":"6 renard"}],"location":"montagne-du-vuache","id":28,"status":"beacon-reconition","created_at":"2023-06-26T06:51:46.147Z","reporting":3},{"reportings":[{"index":6,"score":0.9624217748641968,"category_name":"6 renard"},{"index":1,"score":0.024146825075149536,"category_name":"1 cerf"},{"index":5,"score":0.00433343043550849,"category_name":"5 noise"},{"index":2,"score":0.004246788565069437,"category_name":"2 coup_de_feu_chasseur"},{"index":4,"score":0.004004478454589844,"category_name":"4 moto-cross"}],"location":"montagne-du-vuache","id":29,"status":"beacon-reconition","created_at":"2023-06-26T07:12:39.139Z","reporting":6},{"reportings":[{"index":4,"score":0.9211101531982422,"category_name":"4 moto-cross"},{"index":5,"score":0.07883787155151367,"category_name":"5 noise"},{"index":2,"score":0.00005152688754606061,"category_name":"2 coup_de_feu_chasseur"},{"index":1,"score":4.75408228339802e-7,"category_name":"1 cerf"},{"index":0,"score":2.868017601187489e-9,"category_name":"0 Bruit de fond"}],"location":"montagne-du-vuache","id":30,"status":"beacon-reconition","created_at":"2023-06-26T07:13:12.345Z","reporting":4},{"reportings":[{"index":6,"score":0.9971530437469482,"category_name":"6 renard"},{"index":2,"score":0.0010677132522687316,"category_name":"2 coup_de_feu_chasseur"},{"index":5,"score":0.0009637921466492116,"category_name":"5 noise"},{"index":3,"score":0.0003511819813866168,"category_name":"3 loup"},{"index":1,"score":0.0002703352947719395,"category_name":"1 cerf"}],"location":"montagne-du-vuache","id":31,"status":"beacon-reconition","created_at":"2023-06-26T07:16:16.866Z","reporting":6},{"reportings":[{"index":3,"score":0.9821112751960754,"category_name":"3 loup"},{"index":1,"score":0.00797509029507637,"category_name":"1 cerf"},{"index":5,"score":0.004705417435616255,"category_name":"5 noise"},{"index":4,"score":0.004632924217730761,"category_name":"4 moto-cross"},{"index":6,"score":0.00031751953065395355,"category_name":"6 renard"}],"location":"montagne-du-vuache","id":32,"status":"beacon-reconition","created_at":"2023-06-26T12:38:04.308Z","reporting":3},{"reportings":[{"index":3,"score":0.9830191731452942,"category_name":"3 loup"},{"index":5,"score":0.01669098436832428,"category_name":"5 noise"},{"index":4,"score":0.00017666639178059995,"category_name":"4 moto-cross"},{"index":1,"score":0.00007850252586649731,"category_name":"1 cerf"},{"index":2,"score":0.00001848183455877006,"category_name":"2 coup_de_feu_chasseur"}],"location":"montagne-du-vuache","id":33,"status":"beacon-reconition","created_at":"2023-06-26T12:47:57.688Z","reporting":3},{"reportings":[{"index":3,"score":0.9372518062591553,"category_name":"3 loup"},{"index":5,"score":0.048432011157274246,"category_name":"5 noise"},{"index":1,"score":0.007632799446582794,"category_name":"1 cerf"},{"index":2,"score":0.002541641239076853,"category_name":"2 coup_de_feu_chasseur"},{"index":0,"score":0.0021525707561522722,"category_name":"0 Bruit de fond"}],"location":"montagne-du-vuache","id":34,"status":"beacon-reconition","created_at":"2023-06-26T12:49:41.473Z","reporting":3},{"reportings":[{"index":3,"score":0.9787241816520691,"category_name":"3 loup"},{"index":5,"score":0.02034933678805828,"category_name":"5 noise"},{"index":1,"score":0.0005637595895677805,"category_name":"1 cerf"},{"index":4,"score":0.00022801048180554062,"category_name":"4 moto-cross"},{"index":0,"score":0.00011753585567930713,"category_name":"0 Bruit de fond"}],"location":"montagne-du-vuache","id":35,"status":"beacon-reconition","created_at":"2023-06-26T12:52:00.505Z","reporting":3},{"reportings":[{"index":1,"score":0.9696143865585327,"category_name":"1 cerf"},{"index":5,"score":0.021442553028464317,"category_name":"5 noise"},{"index":3,"score":0.005502257030457258,"category_name":"3 loup"},{"index":0,"score":0.0016050634440034628,"category_name":"0 Bruit de fond"},{"index":4,"score":0.0009220550418831408,"category_name":"4 moto-cross"}],"location":"montagne-du-vuache","id":36,"status":"beacon-reconition","created_at":"2023-06-26T12:52:30.541Z","reporting":1},{"reportings":[{"index":6,"score":0.9884232878684998,"category_name":"6 renard"},{"index":1,"score":0.0070141456089913845,"category_name":"1 cerf"},{"index":5,"score":0.002595089375972748,"category_name":"5 noise"},{"index":4,"score":0.001133617595769465,"category_name":"4 moto-cross"},{"index":3,"score":0.00035466370172798634,"category_name":"3 loup"}],"location":"montagne-du-vuache","id":37,"status":"beacon-reconition","created_at":"2023-06-26T12:53:27.002Z","reporting":6},{"reportings":[{"index":3,"score":0.9612646698951721,"category_name":"3 loup"},{"index":5,"score":0.038563068956136703,"category_name":"5 noise"},{"index":1,"score":0.0000924565174500458,"category_name":"1 cerf"},{"index":0,"score":0.00005395348489400931,"category_name":"0 Bruit de fond"},{"index":4,"score":0.00001645664087845944,"category_name":"4 moto-cross"}],"location":"montagne-du-vuache","id":38,"status":"beacon-reconition","created_at":"2023-06-26T12:54:35.283Z","reporting":3},{"reportings":[{"index":3,"score":0.9121304154396057,"category_name":"3 loup"},{"index":5,"score":0.050409458577632904,"category_name":"5 noise"},{"index":1,"score":0.017047250643372536,"category_name":"1 cerf"},{"index":4,"score":0.011058354750275612,"category_name":"4 moto-cross"},{"index":0,"score":0.004817419219762087,"category_name":"0 Bruit de fond"}],"location":"montagne-du-vuache","id":39,"status":"beacon-reconition","created_at":"2023-06-26T12:56:35.391Z","reporting":3},{"reportings":[{"index":4,"score":0.9986624717712402,"category_name":"4 moto-cross"},{"index":5,"score":0.0006188291008584201,"category_name":"5 noise"},{"index":2,"score":0.0005823274259455502,"category_name":"2 coup_de_feu_chasseur"},{"index":1,"score":0.00013579281221609563,"category_name":"1 cerf"},{"index":0,"score":6.052291041669378e-7,"category_name":"0 Bruit de fond"}],"location":"montagne-du-vuache","id":40,"status":"beacon-reconition","created_at":"2023-06-26T12:57:28.639Z","reporting":4},{"reportings":[{"index":4,"score":0.9994295239448547,"category_name":"4 moto-cross"},{"index":5,"score":0.0005558491684496403,"category_name":"5 noise"},{"index":2,"score":0.000013585273336502723,"category_name":"2 coup_de_feu_chasseur"},{"index":0,"score":6.683335413981695e-7,"category_name":"0 Bruit de fond"},{"index":1,"score":3.982873977292911e-7,"category_name":"1 cerf"}],"location":"montagne-du-vuache","id":41,"status":"beacon-reconition","created_at":"2023-06-26T13:01:51.965Z","reporting":4},{"reportings":[{"index":3,"score":0.9850369095802307,"category_name":"3 loup"},{"index":4,"score":0.007144656497985125,"category_name":"4 moto-cross"},{"index":1,"score":0.0051773712038993835,"category_name":"1 cerf"},{"index":5,"score":0.0017248180229216814,"category_name":"5 noise"},{"index":6,"score":0.000763006042689085,"category_name":"6 renard"}],"location":"montagne-du-vuache","id":42,"status":"beacon-reconition","created_at":"2023-06-26T13:02:57.654Z","reporting":3},{"reportings":[{"index":3,"score":0.9994292855262756,"category_name":"3 loup"},{"index":5,"score":0.0005457710358314216,"category_name":"5 noise"},{"index":4,"score":0.00002161326483474113,"category_name":"4 moto-cross"},{"index":1,"score":0.0000032427674341306556,"category_name":"1 cerf"},{"index":6,"score":1.1574197600339176e-7,"category_name":"6 renard"}],"location":"montagne-du-vuache","id":43,"status":"beacon-reconition","created_at":"2023-06-26T13:06:05.064Z","reporting":3},{"reportings":[{"index":1,"score":0.9310520887374878,"category_name":"1 cerf"},{"index":4,"score":0.02851109951734543,"category_name":"4 moto-cross"},{"index":3,"score":0.01880643144249916,"category_name":"3 loup"},{"index":0,"score":0.01577657088637352,"category_name":"0 Bruit de fond"},{"index":5,"score":0.004578432068228722,"category_name":"5 noise"}],"location":"montagne-du-vuache","id":44,"status":"beacon-reconition","created_at":"2023-06-26T13:06:30.132Z","reporting":1},{"reportings":[{"index":4,"score":0.9964762330055237,"category_name":"4 moto-cross"},{"index":5,"score":0.003262785729020834,"category_name":"5 noise"},{"index":0,"score":0.00025798677233979106,"category_name":"0 Bruit de fond"},{"index":1,"score":0.0000025657127480371855,"category_name":"1 cerf"},{"index":2,"score":3.8794470924585767e-7,"category_name":"2 coup_de_feu_chasseur"}],"location":"montagne-du-vuache","id":45,"status":"beacon-reconition","created_at":"2023-06-26T13:08:06.909Z","reporting":4},{"reportings":[{"index":3,"score":0.9947379231452942,"category_name":"3 loup"},{"index":4,"score":0.0022865075152367353,"category_name":"4 moto-cross"},{"index":5,"score":0.00150055973790586,"category_name":"5 noise"},{"index":6,"score":0.0012161543127149343,"category_name":"6 renard"},{"index":1,"score":0.00019343486928846687,"category_name":"1 cerf"}],"location":"montagne-du-vuache","id":46,"status":"beacon-reconition","created_at":"2023-06-26T13:09:02.591Z","reporting":3},{"reportings":[{"index":4,"score":0.9082762598991394,"category_name":"4 moto-cross"},{"index":1,"score":0.0363541916012764,"category_name":"1 cerf"},{"index":5,"score":0.021652229130268097,"category_name":"5 noise"},{"index":3,"score":0.020331135019659996,"category_name":"3 loup"},{"index":0,"score":0.011695527471601963,"category_name":"0 Bruit de fond"}],"location":"montagne-du-vuache","id":47,"status":"beacon-reconition","created_at":"2023-06-26T13:16:35.496Z","reporting":4},{"reportings":[{"index":3,"score":0.9955703616142273,"category_name":"3 loup"},{"index":1,"score":0.00232608150690794,"category_name":"1 cerf"},{"index":4,"score":0.001034794026054442,"category_name":"4 moto-cross"},{"index":5,"score":0.0008398246136493981,"category_name":"5 noise"},{"index":6,"score":0.0001691828656475991,"category_name":"6 renard"}],"location":"montagne-du-vuache","id":48,"status":"beacon-reconition","created_at":"2023-06-26T13:17:24.629Z","reporting":3},{"reportings":[{"index":3,"score":0.977257251739502,"category_name":"3 loup"},{"index":5,"score":0.014483863487839699,"category_name":"5 noise"},{"index":4,"score":0.005443017464131117,"category_name":"4 moto-cross"},{"index":0,"score":0.0013765634503215551,"category_name":"0 Bruit de fond"},{"index":1,"score":0.0013697348767891526,"category_name":"1 cerf"}],"location":"montagne-du-vuache","id":49,"status":"beacon-reconition","created_at":"2023-06-26T13:59:40.640Z","reporting":3},{"reportings":[{"index":3,"score":0.9898719191551208,"category_name":"3 loup"},{"index":5,"score":0.009879847057163715,"category_name":"5 noise"},{"index":4,"score":0.0001264935708604753,"category_name":"4 moto-cross"},{"index":1,"score":0.00009661782678449526,"category_name":"1 cerf"},{"index":6,"score":0.000015898905985523015,"category_name":"6 renard"}],"location":"montagne-du-vuache","id":50,"status":"beacon-reconition","created_at":"2023-06-26T14:04:42.084Z","reporting":3},{"reportings":[{"index":1,"score":0.9576005935668945,"category_name":"1 cerf"},{"index":4,"score":0.015657545998692513,"category_name":"4 moto-cross"},{"index":6,"score":0.014377178624272346,"category_name":"6 renard"},{"index":5,"score":0.009805777110159397,"category_name":"5 noise"},{"index":2,"score":0.0010469595436006784,"category_name":"2 coup_de_feu_chasseur"}],"location":"montagne-du-vuache","id":51,"status":"beacon-reconition","created_at":"2023-06-26T15:06:14.258Z","reporting":1},{"reportings":[{"index":4,"score":0.9133099913597107,"category_name":"4 moto-cross"},{"index":0,"score":0.05305078625679016,"category_name":"0 Bruit de fond"},{"index":1,"score":0.03311847895383835,"category_name":"1 cerf"},{"index":5,"score":0.00041748170042410493,"category_name":"5 noise"},{"index":2,"score":0.00009316084469901398,"category_name":"2 coup_de_feu_chasseur"}],"location":"montagne-du-vuache","id":52,"status":"beacon-reconition","created_at":"2023-06-26T15:26:10.354Z","reporting":4},{"reportings":[{"index":6,"score":0.9410669803619385,"category_name":"6 renard"},{"index":1,"score":0.036397792398929596,"category_name":"1 cerf"},{"index":4,"score":0.01947661116719246,"category_name":"4 moto-cross"},{"index":0,"score":0.002193047432228923,"category_name":"0 Bruit de fond"},{"index":2,"score":0.000673193484544754,"category_name":"2 coup_de_feu_chasseur"}],"location":"montagne-du-vuache","id":53,"status":"beacon-reconition","created_at":"2023-06-26T15:25:56.131Z","reporting":6},{"reportings":[{"index":4,"score":0.9102076292037964,"category_name":"4 moto-cross"},{"index":0,"score":0.07139746099710464,"category_name":"0 Bruit de fond"},{"index":5,"score":0.008732960559427738,"category_name":"5 noise"},{"index":1,"score":0.0060208747163414955,"category_name":"1 cerf"},{"index":2,"score":0.0031825026962906122,"category_name":"2 coup_de_feu_chasseur"}],"location":"montagne-du-vuache","id":54,"status":"beacon-reconition","created_at":"2023-06-26T15:35:41.608Z","reporting":4},{"reportings":[{"index":3,"score":0.9529442191123962,"category_name":"3 loup"},{"index":4,"score":0.03386696055531502,"category_name":"4 moto-cross"},{"index":5,"score":0.012586195021867752,"category_name":"5 noise"},{"index":1,"score":0.0005533013609237969,"category_name":"1 cerf"},{"index":6,"score":0.000034943233913509175,"category_name":"6 renard"}],"location":"montagne-du-vuache","id":55,"status":"beacon-reconition","created_at":"2023-06-27T07:19:56.909Z","reporting":3},{"reportings":[{"index":3,"score":0.9726028442382812,"category_name":"3 loup"},{"index":5,"score":0.023325782269239426,"category_name":"5 noise"},{"index":4,"score":0.0031220943201333284,"category_name":"4 moto-cross"},{"index":1,"score":0.00048229037201963365,"category_name":"1 cerf"},{"index":6,"score":0.00034644626430235803,"category_name":"6 renard"}],"location":"montagne-du-vuache","id":56,"status":"beacon-reconition","created_at":"2023-06-27T07:22:28.115Z","reporting":3},{"reportings":[{"index":3,"score":0.983970582485199,"category_name":"3 loup"},{"index":5,"score":0.006498793140053749,"category_name":"5 noise"},{"index":1,"score":0.006349069532006979,"category_name":"1 cerf"},{"index":4,"score":0.0025798287242650986,"category_name":"4 moto-cross"},{"index":0,"score":0.00026469308068044484,"category_name":"0 Bruit de fond"}],"location":"montagne-du-vuache","id":57,"status":"beacon-reconition","created_at":"2023-06-27T07:32:40.512Z","reporting":3},{"reportings":[{"index":3,"score":0.9388846158981323,"category_name":"3 loup"},{"index":5,"score":0.052147027105093,"category_name":"5 noise"},{"index":1,"score":0.008032891899347305,"category_name":"1 cerf"},{"index":4,"score":0.0005822160164825618,"category_name":"4 moto-cross"},{"index":2,"score":0.00031234967173077166,"category_name":"2 coup_de_feu_chasseur"}],"location":"montagne-du-vuache","id":58,"status":"beacon-reconition","created_at":"2023-06-27T07:41:59.671Z","reporting":3},{"reportings":[{"index":3,"score":0.999453604221344,"category_name":"3 loup"},{"index":5,"score":0.000366157473763451,"category_name":"5 noise"},{"index":1,"score":0.0001783411717042327,"category_name":"1 cerf"},{"index":6,"score":0.0000010005110198108014,"category_name":"6 renard"},{"index":4,"score":8.815746923573897e-7,"category_name":"4 moto-cross"}],"location":"montagne-du-vuache","id":59,"status":"beacon-reconition","created_at":"2023-06-27T07:47:00.675Z","reporting":3},{"reportings":[{"index":3,"score":0.9949823021888733,"category_name":"3 loup"},{"index":4,"score":0.002607648028060794,"category_name":"4 moto-cross"},{"index":1,"score":0.0012319418601691723,"category_name":"1 cerf"},{"index":5,"score":0.0007065294194035232,"category_name":"5 noise"},{"index":0,"score":0.00024869918706826866,"category_name":"0 Bruit de fond"}],"location":"montagne-du-vuache","id":60,"status":"beacon-reconition","created_at":"2023-06-27T07:48:44.255Z","reporting":3},{"reportings":[{"index":3,"score":0.942757248878479,"category_name":"3 loup"},{"index":5,"score":0.04068871587514877,"category_name":"5 noise"},{"index":1,"score":0.011039990931749344,"category_name":"1 cerf"},{"index":4,"score":0.004734896123409271,"category_name":"4 moto-cross"},{"index":6,"score":0.0003053918480873108,"category_name":"6 renard"}],"location":"montagne-du-vuache","id":61,"status":"beacon-reconition","created_at":"2023-06-27T07:51:33.280Z","reporting":3},{"reportings":[{"index":1,"score":0.9823351502418518,"category_name":"1 cerf"},{"index":6,"score":0.012764330953359604,"category_name":"6 renard"},{"index":5,"score":0.0026129805482923985,"category_name":"5 noise"},{"index":4,"score":0.0010985280387103558,"category_name":"4 moto-cross"},{"index":2,"score":0.0007275296375155449,"category_name":"2 coup_de_feu_chasseur"}],"location":"montagne-du-vuache","id":62,"status":"beacon-reconition","created_at":"2023-06-27T07:51:41.928Z","reporting":1},{"reportings":[{"index":3,"score":0.9451231956481934,"category_name":"3 loup"},{"index":4,"score":0.03280332311987877,"category_name":"4 moto-cross"},{"index":5,"score":0.011649273335933685,"category_name":"5 noise"},{"index":1,"score":0.008751565590500832,"category_name":"1 cerf"},{"index":6,"score":0.0008028739830479026,"category_name":"6 renard"}],"location":"montagne-du-vuache","id":63,"status":"beacon-reconition","created_at":"2023-06-27T07:56:56.175Z","reporting":3},{"reportings":[{"index":3,"score":0.9603626132011414,"category_name":"3 loup"},{"index":5,"score":0.037939343601465225,"category_name":"5 noise"},{"index":1,"score":0.0014237250434234738,"category_name":"1 cerf"},{"index":6,"score":0.00010336982813896611,"category_name":"6 renard"},{"index":2,"score":0.00008156734838848934,"category_name":"2 coup_de_feu_chasseur"}],"location":"montagne-du-vuache","id":64,"status":"beacon-reconition","created_at":"2023-06-27T08:00:45.408Z","reporting":3},{"reportings":[{"index":6,"score":0.9950659275054932,"category_name":"6 renard"},{"index":5,"score":0.0044178166426718235,"category_name":"5 noise"},{"index":3,"score":0.0003264836850576103,"category_name":"3 loup"},{"index":2,"score":0.00012936806888319552,"category_name":"2 coup_de_feu_chasseur"},{"index":4,"score":0.00005702211274183355,"category_name":"4 moto-cross"}],"location":"montagne-du-vuache","id":65,"status":"beacon-reconition","created_at":"2023-06-27T08:02:01.285Z","reporting":6},{"reportings":[{"index":4,"score":0.9567999839782715,"category_name":"4 moto-cross"},{"index":5,"score":0.02702431008219719,"category_name":"5 noise"},{"index":3,"score":0.013276088051497936,"category_name":"3 loup"},{"index":1,"score":0.0025478701572865248,"category_name":"1 cerf"},{"index":2,"score":0.00016409014642704278,"category_name":"2 coup_de_feu_chasseur"}],"location":"montagne-du-vuache","id":66,"status":"beacon-reconition","created_at":"2023-06-27T08:02:30.579Z","reporting":4},{"reportings":[{"index":1,"score":0.9210898280143738,"category_name":"1 cerf"},{"index":3,"score":0.030713433399796486,"category_name":"3 loup"},{"index":5,"score":0.02669583633542061,"category_name":"5 noise"},{"index":4,"score":0.019070418551564217,"category_name":"4 moto-cross"},{"index":0,"score":0.0011299924226477742,"category_name":"0 Bruit de fond"}],"location":"montagne-du-vuache","id":67,"status":"beacon-reconition","created_at":"2023-06-27T08:07:47.629Z","reporting":1},{"reportings":[{"index":4,"score":0.938000500202179,"category_name":"4 moto-cross"},{"index":5,"score":0.04387575015425682,"category_name":"5 noise"},{"index":0,"score":0.015463936142623425,"category_name":"0 Bruit de fond"},{"index":2,"score":0.0020358553156256676,"category_name":"2 coup_de_feu_chasseur"},{"index":6,"score":0.00035668868804350495,"category_name":"6 renard"}],"location":"montagne-du-vuache","id":68,"status":"beacon-reconition","created_at":"2023-06-27T08:13:59.353Z","reporting":4},{"reportings":[{"index":4,"score":0.9887266755104065,"category_name":"4 moto-cross"},{"index":5,"score":0.004942355677485466,"category_name":"5 noise"},{"index":1,"score":0.004941156134009361,"category_name":"1 cerf"},{"index":0,"score":0.0008326226379722357,"category_name":"0 Bruit de fond"},{"index":2,"score":0.0005022930563427508,"category_name":"2 coup_de_feu_chasseur"}],"location":"montagne-du-vuache","id":69,"status":"beacon-reconition","created_at":"2023-06-27T08:15:52.544Z","reporting":4},{"reportings":[{"index":6,"score":0.9705089926719666,"category_name":"6 renard"},{"index":5,"score":0.025798091664910316,"category_name":"5 noise"},{"index":1,"score":0.0036604467313736677,"category_name":"1 cerf"},{"index":3,"score":0.000024197835955419578,"category_name":"3 loup"},{"index":2,"score":0.00000785155043558916,"category_name":"2 coup_de_feu_chasseur"}],"location":"montagne-du-vuache","id":70,"status":"beacon-reconition","created_at":"2023-06-27T08:16:16.171Z","reporting":6},{"reportings":[{"index":3,"score":0.9019986391067505,"category_name":"3 loup"},{"index":5,"score":0.08287816494703293,"category_name":"5 noise"},{"index":4,"score":0.009681204333901405,"category_name":"4 moto-cross"},{"index":1,"score":0.005410115700215101,"category_name":"1 cerf"},{"index":6,"score":0.00002366402441111859,"category_name":"6 renard"}],"location":"montagne-du-vuache","id":71,"status":"beacon-reconition","created_at":"2023-06-27T08:17:13.679Z","reporting":3},{"reportings":[{"index":3,"score":0.9510147571563721,"category_name":"3 loup"},{"index":5,"score":0.04833915829658508,"category_name":"5 noise"},{"index":4,"score":0.0005277029704302549,"category_name":"4 moto-cross"},{"index":0,"score":0.0000696549323038198,"category_name":"0 Bruit de fond"},{"index":1,"score":0.000035739518352784216,"category_name":"1 cerf"}],"location":"montagne-du-vuache","id":72,"status":"beacon-reconition","created_at":"2023-06-27T08:28:25.515Z","reporting":3},{"reportings":[{"index":3,"score":0.990659773349762,"category_name":"3 loup"},{"index":4,"score":0.004820061847567558,"category_name":"4 moto-cross"},{"index":5,"score":0.0031979281920939684,"category_name":"5 noise"},{"index":1,"score":0.0010091953445225954,"category_name":"1 cerf"},{"index":0,"score":0.00015424034791067243,"category_name":"0 Bruit de fond"}],"location":"montagne-du-vuache","id":73,"status":"beacon-reconition","created_at":"2023-06-27T08:31:04.268Z","reporting":3},{"reportings":[{"index":6,"score":0.987149715423584,"category_name":"6 renard"},{"index":1,"score":0.005950322840362787,"category_name":"1 cerf"},{"index":5,"score":0.003987192176282406,"category_name":"5 noise"},{"index":4,"score":0.001988583942875266,"category_name":"4 moto-cross"},{"index":2,"score":0.0008952140342444181,"category_name":"2 coup_de_feu_chasseur"}],"location":"montagne-du-vuache","id":74,"status":"beacon-reconition","created_at":"2023-06-27T08:33:52.271Z","reporting":6},{"reportings":[{"index":6,"score":0.9867514371871948,"category_name":"6 renard"},{"index":5,"score":0.007301991805434227,"category_name":"5 noise"},{"index":2,"score":0.005040606949478388,"category_name":"2 coup_de_feu_chasseur"},{"index":1,"score":0.00044913284364156425,"category_name":"1 cerf"},{"index":4,"score":0.00027035787934437394,"category_name":"4 moto-cross"}],"location":"montagne-du-vuache","id":75,"status":"beacon-reconition","created_at":"2023-06-27T08:38:19.888Z","reporting":6},{"reportings":[{"index":4,"score":0.9772607684135437,"category_name":"4 moto-cross"},{"index":0,"score":0.009289613924920559,"category_name":"0 Bruit de fond"},{"index":2,"score":0.00856862124055624,"category_name":"2 coup_de_feu_chasseur"},{"index":5,"score":0.004830857273191214,"category_name":"5 noise"},{"index":1,"score":0.00004803843694389798,"category_name":"1 cerf"}],"location":"montagne-du-vuache","id":76,"status":"beacon-reconition","created_at":"2023-06-27T08:38:56.170Z","reporting":4},{"reportings":[{"index":3,"score":0.9133721590042114,"category_name":"3 loup"},{"index":5,"score":0.08194106817245483,"category_name":"5 noise"},{"index":1,"score":0.0019266500603407621,"category_name":"1 cerf"},{"index":4,"score":0.0018776565557345748,"category_name":"4 moto-cross"},{"index":2,"score":0.000570432806853205,"category_name":"2 coup_de_feu_chasseur"}],"location":"montagne-du-vuache","id":77,"status":"beacon-reconition","created_at":"2023-06-27T08:44:18.789Z","reporting":3},{"reportings":[{"index":3,"score":0.9488787055015564,"category_name":"3 loup"},{"index":5,"score":0.05019936338067055,"category_name":"5 noise"},{"index":0,"score":0.0005961492424830794,"category_name":"0 Bruit de fond"},{"index":4,"score":0.0002763637457974255,"category_name":"4 moto-cross"},{"index":1,"score":0.00004425523729878478,"category_name":"1 cerf"}],"location":"montagne-du-vuache","id":78,"status":"beacon-reconition","created_at":"2023-06-27T08:51:19.785Z","reporting":3},{"reportings":[{"index":3,"score":0.9552420377731323,"category_name":"3 loup"},{"index":5,"score":0.03916013985872269,"category_name":"5 noise"},{"index":4,"score":0.003219637321308255,"category_name":"4 moto-cross"},{"index":6,"score":0.0010569017613306642,"category_name":"6 renard"},{"index":0,"score":0.0008189425570890307,"category_name":"0 Bruit de fond"}],"location":"montagne-du-vuache","id":79,"status":"beacon-reconition","created_at":"2023-06-27T08:55:16.974Z","reporting":3},{"reportings":[{"index":3,"score":0.9465164542198181,"category_name":"3 loup"},{"index":5,"score":0.04948608949780464,"category_name":"5 noise"},{"index":4,"score":0.0027494451496750116,"category_name":"4 moto-cross"},{"index":6,"score":0.0004926283145323396,"category_name":"6 renard"},{"index":1,"score":0.00045298816985450685,"category_name":"1 cerf"}],"location":"montagne-du-vuache","id":80,"status":"beacon-reconition","created_at":"2023-06-27T09:02:14.481Z","reporting":3},{"reportings":[{"index":3,"score":0.9020051956176758,"category_name":"3 loup"},{"index":5,"score":0.06688400357961655,"category_name":"5 noise"},{"index":4,"score":0.018204087391495705,"category_name":"4 moto-cross"},{"index":1,"score":0.009201508946716785,"category_name":"1 cerf"},{"index":0,"score":0.002591222757473588,"category_name":"0 Bruit de fond"}],"location":"montagne-du-vuache","id":81,"status":"beacon-reconition","created_at":"2023-06-27T09:03:25.047Z","reporting":3},{"reportings":[{"index":3,"score":0.9746214747428894,"category_name":"3 loup"},{"index":5,"score":0.018041888251900673,"category_name":"5 noise"},{"index":4,"score":0.006997693330049515,"category_name":"4 moto-cross"},{"index":1,"score":0.0002930311020463705,"category_name":"1 cerf"},{"index":0,"score":0.00004210862243780866,"category_name":"0 Bruit de fond"}],"location":"montagne-du-vuache","id":82,"status":"beacon-reconition","created_at":"2023-06-27T09:05:56.001Z","reporting":3},{"reportings":[{"index":3,"score":0.9034135937690735,"category_name":"3 loup"},{"index":1,"score":0.046414121985435486,"category_name":"1 cerf"},{"index":4,"score":0.04043886065483093,"category_name":"4 moto-cross"},{"index":5,"score":0.00799117423593998,"category_name":"5 noise"},{"index":6,"score":0.001321877702139318,"category_name":"6 renard"}],"location":"montagne-du-vuache","id":83,"status":"beacon-reconition","created_at":"2023-06-27T09:07:01.221Z","reporting":3},{"reportings":[{"index":6,"score":0.9005913734436035,"category_name":"6 renard"},{"index":1,"score":0.06777746975421906,"category_name":"1 cerf"},{"index":4,"score":0.024328265339136124,"category_name":"4 moto-cross"},{"index":5,"score":0.0063392105512320995,"category_name":"5 noise"},{"index":2,"score":0.0009582023485563695,"category_name":"2 coup_de_feu_chasseur"}],"location":"montagne-du-vuache","id":84,"status":"beacon-reconition","created_at":"2023-06-27T09:08:06.594Z","reporting":6},{"reportings":[{"index":6,"score":0.9312994480133057,"category_name":"6 renard"},{"index":5,"score":0.04872516915202141,"category_name":"5 noise"},{"index":1,"score":0.010515346191823483,"category_name":"1 cerf"},{"index":2,"score":0.00671848701313138,"category_name":"2 coup_de_feu_chasseur"},{"index":4,"score":0.0014551421627402306,"category_name":"4 moto-cross"}],"location":"montagne-du-vuache","id":85,"status":"beacon-reconition","created_at":"2023-06-27T09:44:11.940Z","reporting":6},{"reportings":[{"index":1,"score":0.9576022028923035,"category_name":"1 cerf"},{"index":5,"score":0.03615443781018257,"category_name":"5 noise"},{"index":6,"score":0.003296494949609041,"category_name":"6 renard"},{"index":0,"score":0.002449185121804476,"category_name":"0 Bruit de fond"},{"index":2,"score":0.0003649449208751321,"category_name":"2 coup_de_feu_chasseur"}],"location":"montagne-du-vuache","id":86,"status":"beacon-reconition","created_at":"2023-06-27T09:48:46.693Z","reporting":1},{"reportings":[{"index":3,"score":0.9595714211463928,"category_name":"3 loup"},{"index":5,"score":0.0287299994379282,"category_name":"5 noise"},{"index":4,"score":0.00910231377929449,"category_name":"4 moto-cross"},{"index":6,"score":0.0017136489041149616,"category_name":"6 renard"},{"index":1,"score":0.0006551822298206389,"category_name":"1 cerf"}],"location":"montagne-du-vuache","id":87,"status":"beacon-reconition","created_at":"2023-06-27T09:49:36.661Z","reporting":3},{"reportings":[{"index":3,"score":0.932186484336853,"category_name":"3 loup"},{"index":5,"score":0.0466374009847641,"category_name":"5 noise"},{"index":4,"score":0.010046259500086308,"category_name":"4 moto-cross"},{"index":6,"score":0.005226753652095795,"category_name":"6 renard"},{"index":1,"score":0.004114080220460892,"category_name":"1 cerf"}],"location":"montagne-du-vuache","id":88,"status":"beacon-reconition","created_at":"2023-06-27T09:52:36.591Z","reporting":3},{"reportings":[{"index":3,"score":0.9297777414321899,"category_name":"3 loup"},{"index":5,"score":0.042282164096832275,"category_name":"5 noise"},{"index":4,"score":0.016848981380462646,"category_name":"4 moto-cross"},{"index":1,"score":0.006166234612464905,"category_name":"1 cerf"},{"index":6,"score":0.00422616908326745,"category_name":"6 renard"}],"location":"montagne-du-vuache","id":89,"status":"beacon-reconition","created_at":"2023-06-27T09:56:49.663Z","reporting":3},{"reportings":[{"index":3,"score":0.9118360280990601,"category_name":"3 loup"},{"index":1,"score":0.06923748552799225,"category_name":"1 cerf"},{"index":5,"score":0.011041389778256416,"category_name":"5 noise"},{"index":4,"score":0.0038022687658667564,"category_name":"4 moto-cross"},{"index":6,"score":0.0031324669253081083,"category_name":"6 renard"}],"location":"montagne-du-vuache","id":90,"status":"beacon-reconition","created_at":"2023-06-27T10:12:11.223Z","reporting":3},{"reportings":[{"index":6,"score":0.9576740860939026,"category_name":"6 renard"},{"index":5,"score":0.022222282364964485,"category_name":"5 noise"},{"index":1,"score":0.019278954714536667,"category_name":"1 cerf"},{"index":4,"score":0.0005354961613193154,"category_name":"4 moto-cross"},{"index":3,"score":0.0002501757408026606,"category_name":"3 loup"}],"location":"montagne-du-vuache","id":91,"status":"beacon-reconition","created_at":"2023-06-27T10:14:31.889Z","reporting":6},{"reportings":[{"index":4,"score":0.9549009203910828,"category_name":"4 moto-cross"},{"index":5,"score":0.04344543069601059,"category_name":"5 noise"},{"index":0,"score":0.000882143503986299,"category_name":"0 Bruit de fond"},{"index":2,"score":0.0005770135321654379,"category_name":"2 coup_de_feu_chasseur"},{"index":1,"score":0.0001647218014113605,"category_name":"1 cerf"}],"location":"montagne-du-vuache","id":92,"status":"beacon-reconition","created_at":"2023-06-27T12:05:11.819Z","reporting":4},{"reportings":[{"index":3,"score":0.9694187045097351,"category_name":"3 loup"},{"index":1,"score":0.015759823843836784,"category_name":"1 cerf"},{"index":4,"score":0.011198246851563454,"category_name":"4 moto-cross"},{"index":5,"score":0.002969641936942935,"category_name":"5 noise"},{"index":6,"score":0.00028771889628842473,"category_name":"6 renard"}],"location":"montagne-du-vuache","id":93,"status":"beacon-reconition","created_at":"2023-06-27T12:05:29.731Z","reporting":3},{"reportings":[{"index":3,"score":0.9885209798812866,"category_name":"3 loup"},{"index":5,"score":0.00903237983584404,"category_name":"5 noise"},{"index":0,"score":0.0009483566973358393,"category_name":"0 Bruit de fond"},{"index":1,"score":0.0008074707584455609,"category_name":"1 cerf"},{"index":4,"score":0.0003571000706870109,"category_name":"4 moto-cross"}],"location":"montagne-du-vuache","id":94,"status":"beacon-reconition","created_at":"2023-06-27T12:08:23.179Z","reporting":3},{"reportings":[{"index":6,"score":0.9893187880516052,"category_name":"6 renard"},{"index":5,"score":0.0057964385487139225,"category_name":"5 noise"},{"index":1,"score":0.003296883078292012,"category_name":"1 cerf"},{"index":4,"score":0.0013297884725034237,"category_name":"4 moto-cross"},{"index":2,"score":0.00015404066652990878,"category_name":"2 coup_de_feu_chasseur"}],"location":"montagne-du-vuache","id":95,"status":"beacon-reconition","created_at":"2023-06-27T12:08:28.543Z","reporting":6},{"reportings":[{"index":4,"score":0.9825380444526672,"category_name":"4 moto-cross"},{"index":5,"score":0.010608131997287273,"category_name":"5 noise"},{"index":6,"score":0.004135448019951582,"category_name":"6 renard"},{"index":1,"score":0.001623092102818191,"category_name":"1 cerf"},{"index":0,"score":0.0006081225583329797,"category_name":"0 Bruit de fond"}],"location":"montagne-du-vuache","id":96,"status":"beacon-reconition","created_at":"2023-06-27T12:11:19.595Z","reporting":4},{"reportings":[{"index":6,"score":0.9871260523796082,"category_name":"6 renard"},{"index":5,"score":0.01165518257766962,"category_name":"5 noise"},{"index":1,"score":0.000525627052411437,"category_name":"1 cerf"},{"index":4,"score":0.0003110521356575191,"category_name":"4 moto-cross"},{"index":2,"score":0.0001848839601734653,"category_name":"2 coup_de_feu_chasseur"}],"location":"montagne-du-vuache","id":97,"status":"beacon-reconition","created_at":"2023-06-27T12:11:42.667Z","reporting":6},{"reportings":[{"index":3,"score":0.9783974885940552,"category_name":"3 loup"},{"index":5,"score":0.008468947373330593,"category_name":"5 noise"},{"index":4,"score":0.008345010690391064,"category_name":"4 moto-cross"},{"index":1,"score":0.004349467810243368,"category_name":"1 cerf"},{"index":0,"score":0.000362509919796139,"category_name":"0 Bruit de fond"}],"location":"montagne-du-vuache","id":98,"status":"beacon-reconition","created_at":"2023-06-27T12:11:20.102Z","reporting":3},{"reportings":[{"index":3,"score":0.9800969958305359,"category_name":"3 loup"},{"index":5,"score":0.012279203161597252,"category_name":"5 noise"},{"index":1,"score":0.007246043067425489,"category_name":"1 cerf"},{"index":4,"score":0.00018217312754131854,"category_name":"4 moto-cross"},{"index":6,"score":0.00008962715946836397,"category_name":"6 renard"}],"location":"montagne-du-vuache","id":99,"status":"beacon-reconition","created_at":"2023-06-27T12:13:52.557Z","reporting":3},{"reportings":[{"index":4,"score":0.9242410659790039,"category_name":"4 moto-cross"},{"index":1,"score":0.03160260245203972,"category_name":"1 cerf"},{"index":0,"score":0.027836788445711136,"category_name":"0 Bruit de fond"},{"index":5,"score":0.011546420864760876,"category_name":"5 noise"},{"index":3,"score":0.002681552432477474,"category_name":"3 loup"}],"location":"montagne-du-vuache","id":100,"status":"beacon-reconition","created_at":"2023-06-27T12:15:18.918Z","reporting":4},{"reportings":[{"index":1,"score":0.9137866497039795,"category_name":"1 cerf"},{"index":4,"score":0.041908007115125656,"category_name":"4 moto-cross"},{"index":0,"score":0.028362968936562538,"category_name":"0 Bruit de fond"},{"index":5,"score":0.008544784039258957,"category_name":"5 noise"},{"index":2,"score":0.004093995317816734,"category_name":"2 coup_de_feu_chasseur"}],"location":"montagne-du-vuache","id":101,"status":"beacon-reconition","created_at":"2023-06-27T12:15:47.332Z","reporting":1},{"reportings":[{"index":3,"score":0.9382883310317993,"category_name":"3 loup"},{"index":5,"score":0.061312027275562286,"category_name":"5 noise"},{"index":0,"score":0.00022892295964993536,"category_name":"0 Bruit de fond"},{"index":4,"score":0.00009891018271446228,"category_name":"4 moto-cross"},{"index":1,"score":0.00005619036528514698,"category_name":"1 cerf"}],"location":"montagne-du-vuache","id":102,"status":"beacon-reconition","created_at":"2023-06-27T12:17:32.091Z","reporting":3},{"reportings":[{"index":4,"score":0.9208223819732666,"category_name":"4 moto-cross"},{"index":5,"score":0.051377471536397934,"category_name":"5 noise"},{"index":0,"score":0.017965836450457573,"category_name":"0 Bruit de fond"},{"index":3,"score":0.007066532038152218,"category_name":"3 loup"},{"index":1,"score":0.0014245017664507031,"category_name":"1 cerf"}],"location":"montagne-du-vuache","id":103,"status":"beacon-reconition","created_at":"2023-06-27T12:19:26.061Z","reporting":4},{"reportings":[{"index":3,"score":0.9448053240776062,"category_name":"3 loup"},{"index":5,"score":0.05085255578160286,"category_name":"5 noise"},{"index":4,"score":0.0026300877798348665,"category_name":"4 moto-cross"},{"index":1,"score":0.0007707110489718616,"category_name":"1 cerf"},{"index":0,"score":0.0006468546926043928,"category_name":"0 Bruit de fond"}],"location":"montagne-du-vuache","id":104,"status":"beacon-reconition","created_at":"2023-06-27T12:24:19.928Z","reporting":3},{"reportings":[{"index":3,"score":0.9053675532341003,"category_name":"3 loup"},{"index":5,"score":0.09073791652917862,"category_name":"5 noise"},{"index":0,"score":0.0023626405745744705,"category_name":"0 Bruit de fond"},{"index":4,"score":0.0011857798090204597,"category_name":"4 moto-cross"},{"index":6,"score":0.00016057367611210793,"category_name":"6 renard"}],"location":"montagne-du-vuache","id":105,"status":"beacon-reconition","created_at":"2023-06-27T12:27:28.425Z","reporting":3},{"reportings":[{"index":3,"score":0.918691098690033,"category_name":"3 loup"},{"index":5,"score":0.04960397258400917,"category_name":"5 noise"},{"index":1,"score":0.026077743619680405,"category_name":"1 cerf"},{"index":4,"score":0.003715929575264454,"category_name":"4 moto-cross"},{"index":6,"score":0.0018121032044291496,"category_name":"6 renard"}],"location":"montagne-du-vuache","id":106,"status":"beacon-reconition","created_at":"2023-06-27T12:28:30.529Z","reporting":3},{"reportings":[{"index":3,"score":0.9589006900787354,"category_name":"3 loup"},{"index":5,"score":0.01592683419585228,"category_name":"5 noise"},{"index":4,"score":0.014750507660210133,"category_name":"4 moto-cross"},{"index":1,"score":0.008540119044482708,"category_name":"1 cerf"},{"index":6,"score":0.001259433920495212,"category_name":"6 renard"}],"location":"montagne-du-vuache","id":107,"status":"beacon-reconition","created_at":"2023-06-27T12:29:56.668Z","reporting":3},{"reportings":[{"index":3,"score":0.9930346012115479,"category_name":"3 loup"},{"index":5,"score":0.006908395793288946,"category_name":"5 noise"},{"index":4,"score":0.00003852970985462889,"category_name":"4 moto-cross"},{"index":1,"score":0.00001237874948856188,"category_name":"1 cerf"},{"index":0,"score":0.000005748730927734869,"category_name":"0 Bruit de fond"}],"location":"montagne-du-vuache","id":108,"status":"beacon-reconition","created_at":"2023-06-27T12:34:19.724Z","reporting":3},{"reportings":[{"index":6,"score":0.9992120265960693,"category_name":"6 renard"},{"index":4,"score":0.000468623882625252,"category_name":"4 moto-cross"},{"index":1,"score":0.00027447674074210227,"category_name":"1 cerf"},{"index":5,"score":0.00003723470217664726,"category_name":"5 noise"},{"index":2,"score":0.000004981315669283504,"category_name":"2 coup_de_feu_chasseur"}],"location":"montagne-du-vuache","id":109,"status":"beacon-reconition","created_at":"2023-06-27T12:35:43.268Z","reporting":6},{"reportings":[{"index":3,"score":0.9481493234634399,"category_name":"3 loup"},{"index":5,"score":0.047911372035741806,"category_name":"5 noise"},{"index":4,"score":0.0012957729632034898,"category_name":"4 moto-cross"},{"index":0,"score":0.0012500140583142638,"category_name":"0 Bruit de fond"},{"index":1,"score":0.001027632155455649,"category_name":"1 cerf"}],"location":"montagne-du-vuache","id":110,"status":"beacon-reconition","created_at":"2023-06-27T12:38:00.606Z","reporting":3},{"reportings":[{"index":3,"score":0.9014843106269836,"category_name":"3 loup"},{"index":5,"score":0.08908174186944962,"category_name":"5 noise"},{"index":4,"score":0.008145652711391449,"category_name":"4 moto-cross"},{"index":1,"score":0.0012009277706965804,"category_name":"1 cerf"},{"index":6,"score":0.000049356291128788143,"category_name":"6 renard"}],"location":"montagne-du-vuache","id":111,"status":"beacon-reconition","created_at":"2023-06-27T12:46:24.142Z","reporting":3},{"reportings":[{"index":6,"score":0.9655387997627258,"category_name":"6 renard"},{"index":4,"score":0.023855159059166908,"category_name":"4 moto-cross"},{"index":1,"score":0.00808348972350359,"category_name":"1 cerf"},{"index":5,"score":0.002064982894808054,"category_name":"5 noise"},{"index":0,"score":0.0002621151797939092,"category_name":"0 Bruit de fond"}],"location":"montagne-du-vuache","id":112,"status":"beacon-reconition","created_at":"2023-06-27T12:55:01.501Z","reporting":6},{"reportings":[{"index":3,"score":0.9270725846290588,"category_name":"3 loup"},{"index":5,"score":0.05775757506489754,"category_name":"5 noise"},{"index":4,"score":0.012256166897714138,"category_name":"4 moto-cross"},{"index":1,"score":0.0021407746244221926,"category_name":"1 cerf"},{"index":0,"score":0.00040771006024442613,"category_name":"0 Bruit de fond"}],"location":"montagne-du-vuache","id":113,"status":"beacon-reconition","created_at":"2023-06-27T12:58:47.713Z","reporting":3},{"reportings":[{"index":3,"score":0.9494950175285339,"category_name":"3 loup"},{"index":5,"score":0.050189998000860214,"category_name":"5 noise"},{"index":4,"score":0.00016353034880012274,"category_name":"4 moto-cross"},{"index":1,"score":0.00012084530317224562,"category_name":"1 cerf"},{"index":6,"score":0.000016721598512958735,"category_name":"6 renard"}],"location":"montagne-du-vuache","id":114,"status":"beacon-reconition","created_at":"2023-06-27T13:00:54.878Z","reporting":3},{"reportings":[{"index":3,"score":0.9444801211357117,"category_name":"3 loup"},{"index":5,"score":0.05494781583547592,"category_name":"5 noise"},{"index":4,"score":0.0004763811593875289,"category_name":"4 moto-cross"},{"index":1,"score":0.00004849522883887403,"category_name":"1 cerf"},{"index":0,"score":0.0000210134094231762,"category_name":"0 Bruit de fond"}],"location":"montagne-du-vuache","id":115,"status":"beacon-reconition","created_at":"2023-06-27T13:03:40.770Z","reporting":3},{"reportings":[{"index":3,"score":0.9810925126075745,"category_name":"3 loup"},{"index":5,"score":0.0185274388641119,"category_name":"5 noise"},{"index":6,"score":0.00017491764447186142,"category_name":"6 renard"},{"index":4,"score":0.00009355918882647529,"category_name":"4 moto-cross"},{"index":1,"score":0.00005155331746209413,"category_name":"1 cerf"}],"location":"montagne-du-vuache","id":116,"status":"beacon-reconition","created_at":"2023-06-27T13:07:23.924Z","reporting":3},{"reportings":[{"index":3,"score":0.9075015187263489,"category_name":"3 loup"},{"index":5,"score":0.08434145152568817,"category_name":"5 noise"},{"index":1,"score":0.004133957903832197,"category_name":"1 cerf"},{"index":4,"score":0.0033841165713965893,"category_name":"4 moto-cross"},{"index":0,"score":0.00053911138093099,"category_name":"0 Bruit de fond"}],"location":"montagne-du-vuache","id":117,"status":"beacon-reconition","created_at":"2023-06-27T13:09:24.354Z","reporting":3},{"reportings":[{"index":1,"score":0.9320357441902161,"category_name":"1 cerf"},{"index":3,"score":0.04398668557405472,"category_name":"3 loup"},{"index":5,"score":0.01745096780359745,"category_name":"5 noise"},{"index":4,"score":0.002923213876783848,"category_name":"4 moto-cross"},{"index":0,"score":0.002730659442022443,"category_name":"0 Bruit de fond"}],"location":"montagne-du-vuache","id":118,"status":"beacon-reconition","created_at":"2023-06-27T13:19:21.751Z","reporting":1},{"reportings":[{"index":3,"score":0.9241303205490112,"category_name":"3 loup"},{"index":5,"score":0.07571648061275482,"category_name":"5 noise"},{"index":4,"score":0.00009501348540652543,"category_name":"4 moto-cross"},{"index":1,"score":0.00002988683081639465,"category_name":"1 cerf"},{"index":6,"score":0.000019204686395823956,"category_name":"6 renard"}],"location":"montagne-du-vuache","id":119,"status":"beacon-reconition","created_at":"2023-06-27T13:24:45.403Z","reporting":3},{"reportings":[{"index":1,"score":0.961818277835846,"category_name":"1 cerf"},{"index":5,"score":0.02647063136100769,"category_name":"5 noise"},{"index":4,"score":0.0045563834719359875,"category_name":"4 moto-cross"},{"index":0,"score":0.003693212755024433,"category_name":"0 Bruit de fond"},{"index":2,"score":0.0016252320492640138,"category_name":"2 coup_de_feu_chasseur"}],"location":"montagne-du-vuache","id":120,"status":"beacon-reconition","created_at":"2023-06-27T13:35:06.096Z","reporting":1},{"reportings":[{"index":3,"score":0.9142000079154968,"category_name":"3 loup"},{"index":5,"score":0.08326481282711029,"category_name":"5 noise"},{"index":1,"score":0.0008718100725673139,"category_name":"1 cerf"},{"index":6,"score":0.000789022131357342,"category_name":"6 renard"},{"index":4,"score":0.0006629715790040791,"category_name":"4 moto-cross"}],"location":"montagne-du-vuache","id":121,"status":"beacon-reconition","created_at":"2023-06-27T13:38:57.525Z","reporting":3},{"reportings":[{"index":3,"score":0.9880446791648865,"category_name":"3 loup"},{"index":5,"score":0.009835400618612766,"category_name":"5 noise"},{"index":4,"score":0.0018034405075013638,"category_name":"4 moto-cross"},{"index":1,"score":0.00018762241234071553,"category_name":"1 cerf"},{"index":0,"score":0.00010038921755040064,"category_name":"0 Bruit de fond"}],"location":"montagne-du-vuache","id":122,"status":"beacon-reconition","created_at":"2023-06-27T13:48:49.559Z","reporting":3},{"reportings":[{"index":3,"score":0.9219038486480713,"category_name":"3 loup"},{"index":5,"score":0.07061126083135605,"category_name":"5 noise"},{"index":1,"score":0.004261309280991554,"category_name":"1 cerf"},{"index":4,"score":0.0021369948517531157,"category_name":"4 moto-cross"},{"index":0,"score":0.0009510379750281572,"category_name":"0 Bruit de fond"}],"location":"montagne-du-vuache","id":123,"status":"beacon-reconition","created_at":"2023-06-27T13:50:40.652Z","reporting":3},{"reportings":[{"index":3,"score":0.9209268689155579,"category_name":"3 loup"},{"index":5,"score":0.07735016196966171,"category_name":"5 noise"},{"index":1,"score":0.0009578000754117966,"category_name":"1 cerf"},{"index":2,"score":0.000343254825565964,"category_name":"2 coup_de_feu_chasseur"},{"index":6,"score":0.00017038754594977945,"category_name":"6 renard"}],"location":"montagne-du-vuache","id":124,"status":"beacon-reconition","created_at":"2023-06-27T13:53:20.343Z","reporting":3},{"reportings":[{"index":4,"score":0.9106786251068115,"category_name":"4 moto-cross"},{"index":5,"score":0.06621288508176804,"category_name":"5 noise"},{"index":0,"score":0.020789336413145065,"category_name":"0 Bruit de fond"},{"index":3,"score":0.001779044046998024,"category_name":"3 loup"},{"index":1,"score":0.00039766525151208043,"category_name":"1 cerf"}],"location":"montagne-du-vuache","id":125,"status":"beacon-reconition","created_at":"2023-06-27T13:58:47.262Z","reporting":4},{"reportings":[{"index":3,"score":0.9732891917228699,"category_name":"3 loup"},{"index":4,"score":0.016334732994437218,"category_name":"4 moto-cross"},{"index":5,"score":0.007264628540724516,"category_name":"5 noise"},{"index":1,"score":0.0028233942575752735,"category_name":"1 cerf"},{"index":0,"score":0.00024597608717158437,"category_name":"0 Bruit de fond"}],"location":"montagne-du-vuache","id":126,"status":"beacon-reconition","created_at":"2023-06-27T13:58:50.634Z","reporting":3},{"reportings":[{"index":1,"score":0.9196983575820923,"category_name":"1 cerf"},{"index":5,"score":0.052475906908512115,"category_name":"5 noise"},{"index":4,"score":0.012446116656064987,"category_name":"4 moto-cross"},{"index":6,"score":0.008741508238017559,"category_name":"6 renard"},{"index":0,"score":0.005710460711270571,"category_name":"0 Bruit de fond"}],"location":"montagne-du-vuache","id":127,"status":"beacon-reconition","created_at":"2023-06-27T14:00:47.270Z","reporting":1},{"reportings":[{"index":3,"score":0.9098882079124451,"category_name":"3 loup"},{"index":5,"score":0.05865494906902313,"category_name":"5 noise"},{"index":4,"score":0.028293969109654427,"category_name":"4 moto-cross"},{"index":1,"score":0.001218282151967287,"category_name":"1 cerf"},{"index":0,"score":0.0010046788956969976,"category_name":"0 Bruit de fond"}],"location":"montagne-du-vuache","id":128,"status":"beacon-reconition","created_at":"2023-06-27T14:03:14.281Z","reporting":3},{"reportings":[{"index":3,"score":0.9932103753089905,"category_name":"3 loup"},{"index":5,"score":0.005018572323024273,"category_name":"5 noise"},{"index":6,"score":0.0006073469412513077,"category_name":"6 renard"},{"index":4,"score":0.0005587225896306336,"category_name":"4 moto-cross"},{"index":1,"score":0.00042765968828462064,"category_name":"1 cerf"}],"location":"montagne-du-vuache","id":129,"status":"beacon-reconition","created_at":"2023-06-27T14:06:48.990Z","reporting":3},{"reportings":[{"index":3,"score":0.995419979095459,"category_name":"3 loup"},{"index":5,"score":0.002032273216173053,"category_name":"5 noise"},{"index":1,"score":0.0010697521502152085,"category_name":"1 cerf"},{"index":4,"score":0.0009484604233875871,"category_name":"4 moto-cross"},{"index":6,"score":0.00038028685958124697,"category_name":"6 renard"}],"location":"montagne-du-vuache","id":130,"status":"beacon-reconition","created_at":"2023-06-27T14:08:36.816Z","reporting":3},{"reportings":[{"index":2,"score":0.9074762463569641,"category_name":"2 coup_de_feu_chasseur"},{"index":5,"score":0.08856408298015594,"category_name":"5 noise"},{"index":3,"score":0.0021606828086078167,"category_name":"3 loup"},{"index":1,"score":0.0008346813847310841,"category_name":"1 cerf"},{"index":0,"score":0.0003711239551194012,"category_name":"0 Bruit de fond"}],"location":"montagne-du-vuache","id":131,"status":"beacon-reconition","created_at":"2023-06-27T14:09:22.662Z","reporting":2},{"reportings":[{"index":3,"score":0.9036903977394104,"category_name":"3 loup"},{"index":5,"score":0.060743093490600586,"category_name":"5 noise"},{"index":1,"score":0.02465987764298916,"category_name":"1 cerf"},{"index":0,"score":0.006590171251446009,"category_name":"0 Bruit de fond"},{"index":4,"score":0.0027116709388792515,"category_name":"4 moto-cross"}],"location":"montagne-du-vuache","id":132,"status":"beacon-reconition","created_at":"2023-06-27T14:20:09.181Z","reporting":3},{"reportings":[{"index":3,"score":0.9281841516494751,"category_name":"3 loup"},{"index":5,"score":0.054642826318740845,"category_name":"5 noise"},{"index":4,"score":0.011057402938604355,"category_name":"4 moto-cross"},{"index":2,"score":0.003534343559294939,"category_name":"2 coup_de_feu_chasseur"},{"index":6,"score":0.0015436980174854398,"category_name":"6 renard"}],"location":"montagne-du-vuache","id":133,"status":"beacon-reconition","created_at":"2023-06-27T14:23:05.323Z","reporting":3},{"reportings":[{"index":1,"score":0.9189084768295288,"category_name":"1 cerf"},{"index":5,"score":0.06173728406429291,"category_name":"5 noise"},{"index":0,"score":0.01198253408074379,"category_name":"0 Bruit de fond"},{"index":3,"score":0.0036194815766066313,"category_name":"3 loup"},{"index":4,"score":0.001745617832057178,"category_name":"4 moto-cross"}],"location":"montagne-du-vuache","id":134,"status":"beacon-reconition","created_at":"2023-06-27T14:25:29.360Z","reporting":1},{"reportings":[{"index":4,"score":0.949053943157196,"category_name":"4 moto-cross"},{"index":5,"score":0.02038124017417431,"category_name":"5 noise"},{"index":0,"score":0.014922101981937885,"category_name":"0 Bruit de fond"},{"index":2,"score":0.013410137966275215,"category_name":"2 coup_de_feu_chasseur"},{"index":1,"score":0.002232376951724291,"category_name":"1 cerf"}],"location":"montagne-du-vuache","id":135,"status":"beacon-reconition","created_at":"2023-06-28T06:54:15.299Z","reporting":4},{"reportings":[{"index":4,"score":0.9994156360626221,"category_name":"4 moto-cross"},{"index":5,"score":0.0005597934941761196,"category_name":"5 noise"},{"index":1,"score":0.000017797887267079204,"category_name":"1 cerf"},{"index":2,"score":0.000006715759809594601,"category_name":"2 coup_de_feu_chasseur"},{"index":0,"score":1.747110367489313e-8,"category_name":"0 Bruit de fond"}],"location":"montagne-du-vuache","id":136,"status":"beacon-reconition","created_at":"2023-06-28T06:55:53.828Z","reporting":4},{"reportings":[{"index":3,"score":0.9294565320014954,"category_name":"3 loup"},{"index":6,"score":0.026067517697811127,"category_name":"6 renard"},{"index":5,"score":0.02118850313127041,"category_name":"5 noise"},{"index":1,"score":0.012940913438796997,"category_name":"1 cerf"},{"index":4,"score":0.008484713733196259,"category_name":"4 moto-cross"}],"location":"montagne-du-vuache","id":137,"status":"beacon-reconition","created_at":"2023-06-28T06:56:34.867Z","reporting":3},{"reportings":[{"index":3,"score":0.9985709190368652,"category_name":"3 loup"},{"index":5,"score":0.0013603265397250652,"category_name":"5 noise"},{"index":1,"score":0.000055964497732929885,"category_name":"1 cerf"},{"index":4,"score":0.000011384146091586445,"category_name":"4 moto-cross"},{"index":6,"score":7.037605200821417e-7,"category_name":"6 renard"}],"location":"montagne-du-vuache","id":138,"status":"beacon-reconition","created_at":"2023-06-28T06:59:37.262Z","reporting":3},{"reportings":[{"index":6,"score":0.9997208714485168,"category_name":"6 renard"},{"index":1,"score":0.0002626165805850178,"category_name":"1 cerf"},{"index":2,"score":0.000010506615581107326,"category_name":"2 coup_de_feu_chasseur"},{"index":4,"score":0.000003241613512727781,"category_name":"4 moto-cross"},{"index":3,"score":0.0000011592418331929366,"category_name":"3 loup"}],"location":"montagne-du-vuache","id":139,"status":"beacon-reconition","created_at":"2023-06-28T06:59:28.353Z","reporting":6},{"reportings":[{"index":3,"score":0.9385944604873657,"category_name":"3 loup"},{"index":5,"score":0.026382585987448692,"category_name":"5 noise"},{"index":1,"score":0.01003019418567419,"category_name":"1 cerf"},{"index":0,"score":0.009741969406604767,"category_name":"0 Bruit de fond"},{"index":6,"score":0.009324819780886173,"category_name":"6 renard"}],"location":"montagne-du-vuache","id":140,"status":"beacon-reconition","created_at":"2023-06-28T07:01:50.303Z","reporting":3},{"reportings":[{"index":4,"score":0.9973575472831726,"category_name":"4 moto-cross"},{"index":5,"score":0.0019962070509791374,"category_name":"5 noise"},{"index":1,"score":0.0005358725320547819,"category_name":"1 cerf"},{"index":2,"score":0.0000861663866089657,"category_name":"2 coup_de_feu_chasseur"},{"index":0,"score":0.00001077460365195293,"category_name":"0 Bruit de fond"}],"location":"montagne-du-vuache","id":141,"status":"beacon-reconition","created_at":"2023-06-28T07:03:08.567Z","reporting":4},{"reportings":[{"index":true,"score":0.8543320894241333,"category_name":"5 noise"},{"index":false,"score":0.09414387494325638,"category_name":"0 Bruit de fond"},{"index":false,"score":0.028865870088338852,"category_name":"1 cerf"},{"index":false,"score":0.0140399020165205,"category_name":"4 moto-cross"},{"index":false,"score":0.003990402445197105,"category_name":"3 loup"}],"location":"montagne-du-vuache","id":142,"status":"beacon-reconition","created_at":"2023-06-28T07:09:17.742Z","reporting":true},{"reportings":[{"index":false,"score":0,"category_name":"3 loup"},{"index":false,"score":0,"category_name":"4 moto-cross"},{"index":false,"score":0,"category_name":"1 cerf"},{"index":false,"score":0,"category_name":"0 Bruit de fond"},{"index":false,"score":0,"category_name":"2 coup_de_feu_chasseur"}],"location":"montagne-du-vuache","id":143,"status":"beacon-reconition","created_at":"2023-06-28T07:15:54.464Z","reporting":false},{"reportings":[{"index":true,"score":0.9969452023506165,"category_name":"5 noise"},{"index":false,"score":0.0016679757973179221,"category_name":"3 loup"},{"index":false,"score":0.0008464562706649303,"category_name":"0 Bruit de fond"},{"index":false,"score":0.00018055649707093835,"category_name":"6 renard"},{"index":false,"score":0.00016207993030548096,"category_name":"4 moto-cross"}],"location":"montagne-du-vuache","id":144,"status":"beacon-reconition","created_at":"2023-06-28T07:27:15.485Z","reporting":true},{"reportings":[{"index":3,"score":0.950527548789978,"category_name":"3 loup"},{"index":5,"score":0.048529934138059616,"category_name":"5 noise"},{"index":1,"score":0.0005053064087405801,"category_name":"1 cerf"},{"index":4,"score":0.00042673872667364776,"category_name":"4 moto-cross"},{"index":6,"score":0.000005428390977613162,"category_name":"6 renard"}],"location":"montagne-du-vuache","id":145,"status":"beacon-reconition","created_at":"2023-06-28T07:28:26.407Z","reporting":3},{"reportings":[{"index":6,"score":0.9893063902854919,"category_name":"6 renard"},{"index":1,"score":0.004493308253586292,"category_name":"1 cerf"},{"index":5,"score":0.0031009516678750515,"category_name":"5 noise"},{"index":0,"score":0.0021124924533069134,"category_name":"0 Bruit de fond"},{"index":4,"score":0.0009348439052700996,"category_name":"4 moto-cross"}],"location":"montagne-du-vuache","id":146,"status":"beacon-reconition","created_at":"2023-06-28T07:28:55.509Z","reporting":6},{"reportings":[{"index":4,"score":0.9685585498809814,"category_name":"4 moto-cross"},{"index":5,"score":0.03092784993350506,"category_name":"5 noise"},{"index":2,"score":0.0005088617908768356,"category_name":"2 coup_de_feu_chasseur"},{"index":0,"score":0.000003802220817306079,"category_name":"0 Bruit de fond"},{"index":1,"score":8.399611033382826e-7,"category_name":"1 cerf"}],"location":"montagne-du-vuache","id":147,"status":"beacon-reconition","created_at":"2023-06-28T07:29:17.106Z","reporting":4},{"reportings":[{"index":2,"score":0.8853921294212341,"category_name":"2 coup_de_feu_chasseur"},{"index":5,"score":0.07037431746721268,"category_name":"5 noise"},{"index":0,"score":0.0319148413836956,"category_name":"0 Bruit de fond"},{"index":6,"score":0.004954195581376553,"category_name":"6 renard"},{"index":4,"score":0.003493142779916525,"category_name":"4 moto-cross"}],"location":"montagne-du-vuache","id":148,"status":"beacon-reconition","created_at":"2023-06-28T07:41:50.033Z","reporting":2},{"reportings":[{"index":4,"score":0.8824365139007568,"category_name":"4 moto-cross"},{"index":5,"score":0.07653038948774338,"category_name":"5 noise"},{"index":2,"score":0.022438837215304375,"category_name":"2 coup_de_feu_chasseur"},{"index":0,"score":0.009445657022297382,"category_name":"0 Bruit de fond"},{"index":6,"score":0.004482623655349016,"category_name":"6 renard"}],"location":"montagne-du-vuache","id":149,"status":"beacon-reconition","created_at":"2023-06-28T08:04:41.091Z","reporting":4},{"reportings":[{"index":6,"score":0.9995900988578796,"category_name":"6 renard"},{"index":5,"score":0.0003630337887443602,"category_name":"5 noise"},{"index":1,"score":0.000022984802853898145,"category_name":"1 cerf"},{"index":3,"score":0.00001779627382347826,"category_name":"3 loup"},{"index":2,"score":0.00000595547680859454,"category_name":"2 coup_de_feu_chasseur"}],"location":"montagne-du-vuache","id":150,"status":"beacon-reconition","created_at":"2023-06-28T08:13:19.673Z","reporting":6},{"reportings":[{"index":1,"score":0.9651317000389099,"category_name":"1 cerf"},{"index":5,"score":0.021764110773801804,"category_name":"5 noise"},{"index":4,"score":0.004703691694885492,"category_name":"4 moto-cross"},{"index":0,"score":0.003931736573576927,"category_name":"0 Bruit de fond"},{"index":3,"score":0.00239964690990746,"category_name":"3 loup"}],"location":"montagne-du-vuache","id":151,"status":"beacon-reconition","created_at":"2023-06-28T08:14:21.394Z","reporting":1},{"reportings":[{"index":1,"score":0.8303314447402954,"category_name":"1 cerf"},{"index":5,"score":0.13769479095935822,"category_name":"5 noise"},{"index":4,"score":0.030348561704158783,"category_name":"4 moto-cross"},{"index":6,"score":0.0009045862825587392,"category_name":"6 renard"},{"index":3,"score":0.0004764705372508615,"category_name":"3 loup"}],"location":"montagne-du-vuache","id":152,"status":"beacon-reconition","created_at":"2023-06-28T08:16:38.849Z","reporting":1},{"reportings":[{"index":6,"score":0.919136106967926,"category_name":"6 renard"},{"index":5,"score":0.0757819414138794,"category_name":"5 noise"},{"index":1,"score":0.003488617017865181,"category_name":"1 cerf"},{"index":3,"score":0.0012276752386242151,"category_name":"3 loup"},{"index":4,"score":0.0003068380174227059,"category_name":"4 moto-cross"}],"location":"montagne-du-vuache","id":153,"status":"beacon-reconition","created_at":"2023-06-28T08:32:33.745Z","reporting":6},{"reportings":[{"index":4,"score":0.999405026435852,"category_name":"4 moto-cross"},{"index":5,"score":0.0004903000080958009,"category_name":"5 noise"},{"index":2,"score":0.00010437299351906404,"category_name":"2 coup_de_feu_chasseur"},{"index":1,"score":3.2570028452028055e-7,"category_name":"1 cerf"},{"index":0,"score":1.6996040130834444e-8,"category_name":"0 Bruit de fond"}],"location":"montagne-du-vuache","id":154,"status":"beacon-reconition","created_at":"2023-06-28T08:32:41.513Z","reporting":4}]